squeezellm/__init__.py
squeezellm-0.0.1.dev0.dist-info/METADATA
squeezellm-0.0.1.dev0.dist-info/WHEEL
squeezellm-0.0.1.dev0.dist-info/top_level.txt
squeezellm-0.0.1.dev0.dist-info/RECORD
