Metadata-Version: 2.1
Name: squeezellm
Version: 0.0.1.dev0
Summary: squeezellm
Author: Juncong Moo
Keywords: squeezellm
Classifier: Programming Language :: Python :: 3
Classifier: Programming Language :: Python :: 3.8
Classifier: Programming Language :: Python :: 3.9
Classifier: Programming Language :: Python :: 3.10
Requires-Dist: torch
